notes_mcp.py
notes_mcp-0.1.4.dist-info/METADATA
notes_mcp-0.1.4.dist-info/WHEEL
notes_mcp-0.1.4.dist-info/entry_points.txt
notes_mcp-0.1.4.dist-info/licenses/LICENCE
notes_mcp-0.1.4.dist-info/RECORD
