Metadata-Version: 2.4
Name: notes-mcp
Version: 0.1.4
Summary: MCP for managing markdown notes with YAML frontmatter
Author-email: Edvard Lindelöf <edvardlindelof@gmail.com>
License-File: LICENCE
Requires-Python: >=3.13
Requires-Dist: fastmcp>=2.12.3
Requires-Dist: pyyaml>=6.0.2
